m_am_rom.sv
module m_am_rom #(
    parameter   int NUM_SBOX   = 14833,
    localparam  int SBOX_SIZE  = 256
)(
    input   wire [13:0] w_sel_sbox,
    input   wire [7:0]  w_in_num,
    output  wire [7:0]  w_out_num
);
    logic [7:0] rom_array [0:NUM_SBOX-1][0:SBOX_SIZE-1];
    initial begin
        $readmemh("sbox_patterns.mem", rom_array);
    end
    assign w_out_num = rom_array[w_sel_sbox][w_in_num];
endmodule

module m_sel_sbox(
    input   logic w_clk,
    input   logic         w_rst_n,
    input   logic         w_en,
    output  logic [13:0]  r_out_rnd
);
    logic [511:0] q;
    logic [511:0] q_left;
    logic [511:0] q_right;

    assign q_left = {q[0], q[511:1]};
    assign q_right = {q[510:0], q[511]};

    always @(posedge w_clk) begin
        if (!w_rst_n) begin
            q <= 512'ha5a5_5a5a_1234_5678_9abc_def0_ffff_0000_eeee_1111_bbbb_2222_7777_8888_9999_aaaa;
        end else if (w_en) begin
            q <= q_left ^ (q | q_right);
        end
    end
    assign r_out_rnd = q[13:0];
endmodule

// module m_sliding_window_ctrl(
// )

module m_top(
    input wire w_clk
);
    // Sbox selector signals
    wire    [13:0]  w_raw_bits;
    wire    [13:0]  w_pattern_sel;
    // Internal register
    reg     [127:0] r_state;
    reg     [6:0]   r_window_pointer;
    // Next_state_register
    reg     [7:0]   r_window_out;
    // Control signal: reset and enable
    reg     w_rst_n;
    reg     w_en_RND;

    m_sel_sbox mX (
        .w_clk(w_clk),
        .w_rst_n(w_rst_n),
        .w_en(w_en_RND),
        .r_out_rnd(w_raw_bits)
    );

    m_am_rom mY (
        .w_sel_sbox(w_pattern_sel),
        .w_in_num(r_state[r_window_pointer +: 8]),
        .w_out_num(r_window_out)
    );

    // always @(*) begin
    //     if (w_raw_bits >= 14'd14833)
    //         w_pattern_sel = w_raw_bits - 14'd14833;
    //     else
    //         w_pattern_sel = w_raw_bits;
    // end
    assign w_pattern_sel = (w_raw_bits >= 14'd14833) ? w_raw_bits - 14'd14833 : w_raw_bits;

    always @(posedge w_clk) begin
        if (!w_rst_n) begin
            r_state <= 128'h8080_8080_8080_8080_8080_8080_8080_8080;
            r_window_pointer <= 7'h0;
        end else if (w_en_RND) begin
            r_state[r_window_pointer +: 8] <= r_window_out;
            if (r_window_pointer >= 7'd120) begin
                r_window_pointer <= 7'd0;
            end else begin
                r_window_pointer <= r_window_pointer + 7'd1;
            end
        end
    end
endmodule

m_sim.sv
`timescale 1ns/10ps
module m_sim(w_clk, w_cc);
    input wire w_clk;
    input wire [31:0] w_cc;
    m_top m(w_clk);
    initial begin
        m.w_rst_n <= 1'b0;
        m.w_en_RND   <= 1'b0;
    end

    initial #99 forever #100 begin 
        $display("CC%1d %h",
    w_cc, m.r_state);
    end
    
    initial #150 begin
        m.w_rst_n <= 1'b1;
        m.w_en_RND <= 1'b1;
    end
endmodule

m_top_wrapper.sv
`timescale 1ns/100ps
`default_nettype none
module m_top_wrapper();
    reg r_clk = 0;
    initial #50 forever #50 r_clk = ~r_clk;
    reg [31:0] r_cc = 1; always @(posedge r_clk) r_cc = r_cc + 1;
    initial #100000 begin $display("Time out"); $finish; end
    m_sim m(r_clk, r_cc);
    initial $dumpvars(0, m);
endmodule

// top_wrapper is a wrapper of the testbench, it:
// - generate the clock signal
// - stop simulation in case inf loop
// - put in a counting signal
// - use $dumpvar(0, m) to generate a waveform of every signal inside testbench

dump.vcd
$date
	Sun May 31 11:58:23 2026
$end
$version
	Icarus Verilog
$end
$timescale
	10ps
$end
$scope module m_top_wrapper $end
$scope module m $end
$var wire 32 ! w_cc [31:0] $end
$var wire 1 " w_clk $end
$scope module m $end
$var wire 1 " w_clk $end
$var wire 14 # w_raw_bits [13:0] $end
$var wire 14 $ w_pattern_sel [13:0] $end
$var wire 8 % r_window_out [7:0] $end
$var reg 128 & r_state [127:0] $end
$var reg 7 ' r_window_pointer [6:0] $end
$var reg 1 ( w_en_RND $end
$var reg 1 ) w_rst_n $end
$scope module mX $end
$var wire 1 " w_clk $end
$var wire 1 ( w_en $end
$var wire 1 ) w_rst_n $end
$var wire 14 * r_out_rnd [13:0] $end
$var wire 512 + q_right [511:0] $end
$var wire 512 , q_left [511:0] $end
$var reg 512 - q [511:0] $end
$upscope $end
$scope module mY $end
$var wire 8 . w_in_num [7:0] $end
$var wire 8 / w_out_num [7:0] $end
$var wire 14 0 w_sel_sbox [13:0] $end
$var parameter 32 1 NUM_SBOX $end
$var parameter 32 2 SBOX_SIZE $end
$upscope $end
$upscope $end
$upscope $end
$upscope $end
$enddefinitions $end
$comment Show the parameter values. $end
$dumpall
b100000000 2
b11100111110001 1
$end
#0
$dumpvars
bx 0
bx /
bx .
bx -
bx ,
bx +
bx *
0)
0(
bx '
bx &
bx %
bx $
bx #
0"
b1 !
$end
#10000
b10 %
b10 /
b10101010101010 $
b10101010101010 0
b101001011010010101011010010110100001001000110100010101100111100010011010101111001101111011110000111111111111111100000000000000001110111011101110000100010001000110111011101110110010001000100010011101110111011110001000100010001001100110011001101010101010101 ,
b10100101101001010101101001011010000100100011010001010110011110001001101010111100110111101111000011111111111111110000000000000000111011101110111000010001000100011011101110111011001000100010001001110111011101111000100010001000100110011001100110101010101010100 +
b10101010101010 #
b10101010101010 *
b1010010110100101010110100101101000010010001101000101011001111000100110101011110011011110111100001111111111111111000000000000000011101110111011100001000100010001101110111011101100100010001000100111011101110111100010001000100010011001100110011010101010101010 -
b10000000 .
b0 '
b10000000100000001000000010000000100000001000000010000000100000001000000010000000100000001000000010000000100000001000000010000000 &
b10 !
1"
#15000
1(
1)
0"
#20000
b10101010101011 $
b10101010101011 0
b10000000000000000000000000000000000000000000000000000000000000000000000000000000000000000000000000000000000000000000000000000000000000000000000000000000000000000000000000000000000000000000000000000000000000000000000000000000000000000000000000000000000000001101111010011110101010011110100110011111101100110110101011100010111110010101000111001000010001001100000000000000010000000000000011000100010001001001110111011101100100010001000101111011101110111110001000100010001011101110111011111011101110111001010101010101 ,
b110111101001111010101001111010011001111110110011011010101110001011111001010100011100100001000100110000000000000001000000000000001100010001000100100111011101110110010001000100010111101110111011111000100010001000101110111011101111101110111011100101010101010110 +
b10101010101011 #
b10101010101011 *
b1 '
b1000000 %
b1000000 /
b1 .
b10000000100000001000000010000000100000001000000010000000100000001000000010000000100000001000000010000000100000001000000000000010 &
b11011110100111101010100111101001100111111011001101101010111000101111100101010001110010000100010011000000000000000100000000000000110001000100010010011101110111011001000100010001011110111011101111100010001000100010111011101110111110111011101110010101010101011 -
b11 !
1"
#25000
0"
#30000
b10101010101010 $
b10101010101010 0
b1000000000000000000000000000000000000000000000000000000000000000000000000000000000000000000000000000000000000000000000000000000000000000000000000000000000000000000000000000000000000000000000000000000000000000000000000000000000000000000000000000000000000011001000011110000101011110000111101110000001011100100101010010110100001110101101100111100111011111010000000000000111000000000000110101110111011111111000100010001011110111011101101000010001000100001011101110111011010001000100010000010001000100111010101010101 ,
b1100100001111000010101111000011110111000000101110010010101001011010000111010110110011110011101111101000000000000011100000000000011010111011101111111100010001000101111011101110110100001000100010000101110111011101101000100010001000001000100010011101010101010101 +
b10101010101010 #
b10101010101010 *
b10000000000000000000000000000000000000000000000000000000000000000000000000000000000000000000000000000000000000000000000000000000000000000000000000000000000000000000000000000000000000000000000000000000000000000000000000000000000000000000000000000000000000110010000111100001010111100001111011100000010111001001010100101101000011101011011001111001110111110100000000000001110000000000001101011101110111111110001000100010111101110111011010000100010001000010111011101110110100010001000100000100010001001110101010101010 -
b10 '
b1000 %
b1000 /
b100000 .
b10000000100000001000000010000000100000001000000010000000100000001000000010000000100000001000000010000000100000001000000010000000 &
b100 !
1"
#35000
0"
#40000
b101010101010 $
b101010101010 0
b1100000000000000000000000000000000000000000000000000000000000000000000000000000000000000000000000000000000000000000000000000000000000000000000000000000000000000000000000000000000000000000000000000000000000000000000000000000000000000000000000000000000000110111100110001001101010001001100001001000011010011111101011110100110011000101001011100011100010000011000000000001100100000000001100101000100010000000101110111011010000100010001001100111011101110011010001000100010011011101110111000111011101111100010101010101 ,
b10000000000000000000000000000000000000000000000000000000000000000000000000000000000000000000000000000000000000000000000000000000000000000000000000000000000000000000000000000000000000000000000000000000000000000000000000000000000000000000000000000000000011011110011000100110101000100110000100100001101001111110101111010011001100010100101110001110001000001100000000000110010000000000110010100010001000000010111011101101000010001000100110011101110111001101000100010001001101110111011100011101110111110001010101010101 +
b101010101010 #
b101010101010 *
b11 '
b10000000 %
b10000000 /
b100 .
b10000000100000001000000010000000100000001000000010000000100000001000000010000000100000001000000010000000100000001000000000100000 &
b11000000000000000000000000000000000000000000000000000000000000000000000000000000000000000000000000000000000000000000000000000000000000000000000000000000000000000000000000000000000000000000000000000000000000000000000000000000000000000000000000000000000001101111001100010011010100010011000010010000110100111111010111101001100110001010010111000111000100000110000000000011001000000000011001010001000100000001011101110110100001000100010011001110111011100110100010001000100110111011101110001110111011111000101010101010 -
b101 !
1"
#45000
0"
#50000
b1101010101010 $
b1101010101010 0
b1010000000000000000000000000000000000000000000000000000000000000000000000000000000000000000000000000000000000000000000000000000000000000000000000000000000000000000000000000000000000000000000000000000000000000000000000000000000000000000000000000000000001100100011101011111001011011111010011111100110011110000001010000111101110101101111010010110010111000110100000000011011110000000011011101101110111000001101000100010011001110111011111011100010001001110011011101110111110010001000100101100010001000010110101010101 ,
b1000000000000000000000000000000000000000000000000000000000000000000000000000000000000000000000000000000000000000000000000000000000000000000000000000000000000000000000000000000000000000000000000000000000000000000000000000000000000000000000000000000000110010001110101111100101101111101001111110011001111000000101000011110111010110111101001011001011100011010000000001101111000000001101110110111011100000110100010001001100111011101111101110001000100111001101110111011111001000100010010110001000100001011010101010101 +
b1101010101010 #
b1101010101010 *
b10100000000000000000000000000000000000000000000000000000000000000000000000000000000000000000000000000000000000000000000000000000000000000000000000000000000000000000000000000000000000000000000000000000000000000000000000000000000000000000000000000000000011001000111010111110010110111110100111111001100111100000010100001111011101011011110100101100101110001101000000000110111100000000110111011011101110000011010001000100110011101110111110111000100010011100110111011101111100100010001001011000100010000101101010101010 -
b100 '
b1 %
b1 /
b1000000 .
b10000000100000001000000010000000100000001000000010000000100000001000000010000000100000001000000010000000100000001000010000000000 &
b110 !
1"
#55000
0"
#60000
b1001010101010 $
b1001010101010 0
b1011000000000000000000000000000000000000000000000000000000000000000000000000000000000000000000000000000000000000000000000000000000000000000000000000000000000000000000000000000000000000000000000000000000000000000000000000000000000000000000000000000000011011110110001010000111010010000011110000011101110001000011011001100001000101001000011110101110100101100110000000110010001000000110010001001000100100011001101110111110111000100010000010010111011111001110010001000100001111011101111101010111011100110100101010101 ,
b1100000000000000000000000000000000000000000000000000000000000000000000000000000000000000000000000000000000000000000000000000000000000000000000000000000000000000000000000000000000000000000000000000000000000000000000000000000000000000000000000000000001101111011000101000011101001000001111000001110111000100001101100110000100010100100001111010111010010110011000000011001000100000011001000100100010010001100110111011111011100010001000001001011101111100111001000100010000111101110111110101011101110011010010101010101 +
b1001010101010 #
b1001010101010 *
b101 '
b0 %
b0 /
b0 .
b10000000100000001000000010000000100000001000000010000000100000001000000010000000100000001000000010000000100000001000000000010000 &
b10110000000000000000000000000000000000000000000000000000000000000000000000000000000000000000000000000000000000000000000000000000000000000000000000000000000000000000000000000000000000000000000000000000000000000000000000000000000000000000000000000000000110111101100010100001110100100000111100000111011100010000110110011000010001010010000111101011101001011001100000001100100010000001100100010010001001000110011011101111101110001000100000100101110111110011100100010001000011110111011111010101110111001101001010101010 -
b111 !
1"
#65000
0"
#70000
b1111010101010 $
b1111010101010 0
b1010100000000000000000000000000000000000000000000000000000000000000000000000000000000000000000000000000000000000000000000000000000000000000000000000000000000000000000000000000000000000000000000000000000000000000000000000000000000000000000000000000000110010000101011011001100011111000110001000110001001011100110010111010011101101111100110000101000111101011101000001101111011100001101111011111101111110110111001000100000100101110111000111110100010000111001111011101110011000010001000001010100010011100111101010101 ,
b1010000000000000000000000000000000000000000000000000000000000000000000000000000000000000000000000000000000000000000000000000000000000000000000000000000000000000000000000000000000000000000000000000000000000000000000000000000000000000000000000000000011001000010101101100110001111100011000100011000100101110011001011101001110110111110011000010100011110101110100000110111101110000110111101111110111111011011100100010000010010111011100011111010001000011100111101110111001100001000100000101010001001110011110101010101 +
b1111010101010 #
b1111010101010 *
b10101000000000000000000000000000000000000000000000000000000000000000000000000000000000000000000000000000000000000000000000000000000000000000000000000000000000000000000000000000000000000000000000000000000000000000000000000000000000000000000000000000001100100001010110110011000111110001100010001100010010111001100101110100111011011111001100001010001111010111010000011011110111000011011110111111011111101101110010001000001001011101110001111101000100001110011110111011100110000100010000010101000100111001111010101010 -
b110 '
b1000 !
1"
#75000
0"
#80000
b11000010101010 $
b11000010101010 0
b1010110000000000000000000000000000000000000000000000000000000000000000000000000000000000000000000000000000000000000000000000000000000000000000000000000000000000000000000000000000000000000000000000000000000000000000000000000000000000000000000000000001101111001101010010111010110000101101011101101011111010011101110100011110001001000011101001101101100001010001100011001000010010011001000010000001000000100100111101110001111101000100101100000110111001100111000010001001110100111011100011010110111110011100001010101 ,
b1011000000000000000000000000000000000000000000000000000000000000000000000000000000000000000000000000000000000000000000000000000000000000000000000000000000000000000000000000000000000000000000000000000000000000000000000000000000000000000000000000000110111100110101001011101011000010110101110110101111101001110111010001111000100100001110100110110110000101000110001100100001001001100100001000000100000010010011110111000111110100010010110000011011100110011100001000100111010011101110001101011011111001110000101010101 +
b11000010101010 #
b11000010101010 *
b111 '
b10101100000000000000000000000000000000000000000000000000000000000000000000000000000000000000000000000000000000000000000000000000000000000000000000000000000000000000000000000000000000000000000000000000000000000000000000000000000000000000000000000000011011110011010100101110101100001011010111011010111110100111011101000111100010010000111010011011011000010100011000110010000100100110010000100000010000001001001111011100011111010001001011000001101110011001110000100010011101001110111000110101101111100111000010101010 -
b1001 !
1"
#85000
0"
#90000
b100110101010 $
b100110101010 0
b1010101000000000000000000000000000000000000000000000000000000000000000000000000000000000000000000000000000000000000000000000000000000000000000000000000000000000000000000000000000000000000000000000000000000000000000000000000000000000000000000000000011001000111001011110100010101001101001010001001010000011110001000110110001011111100110001111001001010011011011010110111100111111110111100111000011100001111111100001001011000001101111101010001100100111011100100111011111000111100010010110010100100001110010011010101 ,
b1010100000000000000000000000000000000000000000000000000000000000000000000000000000000000000000000000000000000000000000000000000000000000000000000000000000000000000000000000000000000000000000000000000000000000000000000000000000000000000000000000001100100011100101111010001010100110100101000100101000001111000100011011000101111110011000111100100101001101101101011011110011111111011110011100001110000111111110000100101100000110111110101000110010011101110010011101111100011110001001011001010010000111001001101010101 +
b100110101010 #
b100110101010 *
b10101010000000000000000000000000000000000000000000000000000000000000000000000000000000000000000000000000000000000000000000000000000000000000000000000000000000000000000000000000000000000000000000000000000000000000000000000000000000000000000000000000110010001110010111101000101010011010010100010010100000111100010001101100010111111001100011110010010100110110110101101111001111111101111001110000111000011111111000010010110000011011111010100011001001110111001001110111110001111000100101100101001000011100100110101010 -
b1000000 %
b1000000 /
b10000000 .
b1000 '
b1010 !
1"
#95000
0"
#100000
b10100111001 $
b10100111001 0
b1010101100000000000000000000000000000000000000000000000000000000000000000000000000000000000000000000000000000000000000000000000000000000000000000000000000000000000000000000000000000000000000000000000000000000000000000000000000000000000000000000000110111101100111010000110110101111001111011011111011000110001011101100101011010000011101011000111111011110010010010100100011100000000100011100100110010011000000010011111010100011001000001011011011111100010011111100010000101100010111110101110111110011001111110010101 ,
b1010110000000000000000000000000000000000000000000000000000000000000000000000000000000000000000000000000000000000000000000000000000000000000000000000000000000000000000000000000000000000000000000000000000000000000000000000000000000000000000000000011011110110011101000011011010111100111101101111101100011000101110110010101101000001110101100011111101111001001001010010001110000000010001110010011001001100000001001111101010001100100000101101101111110001001111110001000010110001011111010111011111001100111111001010101 +
b11111100101010 #
b11111100101010 *
b1001 '
b100 %
b100 /
b100000 .
b10000000100000001000000010000000100000001000000010000000100000001000000010000000100000001000000010000000100000000100000000010000 &
b10101011000000000000000000000000000000000000000000000000000000000000000000000000000000000000000000000000000000000000000000000000000000000000000000000000000000000000000000000000000000000000000000000000000000000000000000000000000000000000000000000001101111011001110100001101101011110011110110111110110001100010111011001010110100000111010110001111110111100100100101001000111000000001000111001001100100110000000100111110101000110010000010110110111111000100111111000100001011000101111101011101111100110011111100101010 -
b1011 !
1"
#105000
0"
#110000
b10000011101010 $
b10000011101010 0
b1010101010000000000000000000000000000000000000000000000000000000000000000000000000000000000000000000000000000000000000000000000000000000000000000000000000000000000000000000000000000000000000000000000000000000000000000000000000000000000000000000001100100001011100011001100100101000111000010010000010101101011010001011101010011000110001010101100000010001111111110111110110010000001110110011111101111110100000111110000010110110111100011010010010000010111110000010111001101010110100000101000100001110111000001110101 ,
b1010101000000000000000000000000000000000000000000000000000000000000000000000000000000000000000000000000000000000000000000000000000000000000000000000000000000000000000000000000000000000000000000000000000000000000000000000000000000000000000000000110010000101110001100110010010100011100001001000001010110101101000101110101001100011000101010110000001000111111111011111011001000000111011001111110111111010000011111000001011011011110001101001001000001011111000001011100110101011010000010100010000111011100000111010101 +
b10000011101010 #
b10000011101010 *
b10101010100000000000000000000000000000000000000000000000000000000000000000000000000000000000000000000000000000000000000000000000000000000000000000000000000000000000000000000000000000000000000000000000000000000000000000000000000000000000000000000011001000010111000110011001001010001110000100100000101011010110100010111010100110001100010101011000000100011111111101111101100100000011101100111111011111101000001111100000101101101111000110100100100000101111100000101110011010101101000001010001000011101110000011101010 -
b1010 '
b10000000 %
b10000000 /
b10 .
b10000000100000001000000010000000100000001000000010000000100000001000000010000000100000001000000010000000100000000000100000010000 &
b1100 !
1"
#115000
0"
#120000
b1000110001010 $
b1000110001010 0
b1010101011000000000000000000000000000000000000000000000000000000000000000000000000000000000000000000000000000000000000000000000000000000000000000000000000000000000000000000000000000000000000000000000000000000000000000000000000000000000000000000011011110011010010110111011111101101100100111111000110101001010011011010001011110101101011010101010000111011000000000100000101111000011000101110000001000000110001100001000110100100100010110011111111000110100001000110100111001010100110001101101110011000100100011000101 ,
b1010101100000000000000000000000000000000000000000000000000000000000000000000000000000000000000000000000000000000000000000000000000000000000000000000000000000000000000000000000000000000000000000000000000000000000000000000000000000000000000000001101111001101001011011101111110110110010011111100011010100101001101101000101111010110101101010101000011101100000000010000010111100001100010111000000100000011000110000100011010010010001011001111111100011010000100011010011100101010011000110110111001100010010001100010101 +
b1000110001010 #
b1000110001010 *
b1011 '
b10000 %
b10000 /
b1000000 .
b10000000100000001000000010000000100000001000000010000000100000001000000010000000100000001000000010000000100000100000000000010000 &
b10101010110000000000000000000000000000000000000000000000000000000000000000000000000000000000000000000000000000000000000000000000000000000000000000000000000000000000000000000000000000000000000000000000000000000000000000000000000000000000000000000110111100110100101101110111111011011001001111110001101010010100110110100010111101011010110101010100001110110000000001000001011110000110001011100000010000001100011000010001101001001000101100111111110001101000010001101001110010101001100011011011100110001001000110001010 -
b1101 !
1"
#125000
0"
#130000
b101101001 $
b101101001 0
b1010101010100000000000000000000000000000000000000000000000000000000000000000000000000000000000000000000000000000000000000000000000000000000000000000000000000000000000000000000000000000000000000000000000000000000000000000000000000000000000000000110010001110011110100100010000001001011111100000101100101111011110010011011010000101001010010101011001100010100000001110001101000100110101101001000011100001101011010011101100111111110110101110000000101100110011101100111100111010111101011001001001110101111110110101101 ,
b1010101010000000000000000000000000000000000000000000000000000000000000000000000000000000000000000000000000000000000000000000000000000000000000000000000000000000000000000000000000000000000000000000000000000000000000000000000000000000000000000011001000111001111010010001000000100101111110000010110010111101111001001101101000010100101001010101100110001010000000111000110100010011010110100100001110000110101101001110110011111111011010111000000010110011001110110011110011101011110101100100100111010111111011010110101 +
b11101101011010 #
b11101101011010 *
b10101010101000000000000000000000000000000000000000000000000000000000000000000000000000000000000000000000000000000000000000000000000000000000000000000000000000000000000000000000000000000000000000000000000000000000000000000000000000000000000000001100100011100111101001000100000010010111111000001011001011110111100100110110100001010010100101010110011000101000000011100011010001001101011010010000111000011010110100111011001111111101101011100000001011001100111011001111001110101111010110010010011101011111101101011010 -
b1100 '
b10000000 %
b10000000 /
b1000 .
b10000000100000001000000010000000100000001000000010000000100000001000000010000000100000001000000010000000100000001000000000010000 &
b1110 !
1"
#135000
0"
#140000
b1001010010 $
b1001010010 0
b1010101010110000000000000000000000000000000000000000000000000000000000000000000000000000000000000000000000000000000000000000000000000000000000000000000000000000000000000000000000000000000000000000000000000000000000000000000000000000000000000001101111011001110000111110111000011111010000010001101011101000010001111110010011001101111011110101010111010110110000011001011001101111100101001111100110010011001010011110001011100000000100101001000001101011101110001011100011100010100001010111111111000101000000100101001 ,
b1010101011000000000000000000000000000000000000000000000000000000000000000000000000000000000000000000000000000000000000000000000000000000000000000000000000000000000000000000000000000000000000000000000000000000000000000000000000000000000000000110111101100111000011111011100001111101000001000110101110100001000111111001001100110111101111010101011101011011000001100101100110111110010100111110011001001100101001111000101110000000010010100100000110101110111000101110001110001010000101011111111100010100000010010100101 +
b1001010010 #
b1001010010 *
b1101 '
b10000000 %
b10000000 /
b1000000 .
b10000000100000001000000010000000100000001000000010000000100000001000000010000000100000001000000010000000100010000000000000010000 &
b10101010101100000000000000000000000000000000000000000000000000000000000000000000000000000000000000000000000000000000000000000000000000000000000000000000000000000000000000000000000000000000000000000000000000000000000000000000000000000000000000011011110110011100001111101110000111110100000100011010111010000100011111100100110011011110111101010101110101101100000110010110011011111001010011111001100100110010100111100010111000000001001010010000011010111011100010111000111000101000010101111111110001010000001001010010 -
b1111 !
1"
#145000
0"
#150000
b11111011110 $
b11111011110 0
b1010101010101000000000000000000000000000000000000000000000000000000000000000000000000000000000000000000000000000000000000000000000000000000000000000000000000000000000000000000000000000000000000000000000000000000000000000000000000000000000000011001000010111001001100000100100110000011000111011001010001100111011000001111110111001000010000101010100010100101000110111010111001000011101111000011101111110111011110001011010010000001111101111100011001010001001011010010110010110110011010100000000101101100001111101111 ,
b1010101010100000000000000000000000000000000000000000000000000000000000000000000000000000000000000000000000000000000000000000000000000000000000000000000000000000000000000000000000000000000000000000000000000000000000000000000000000000000000001100100001011100100110000010010011000001100011101100101000110011101100000111111011100100001000010101010001010010100011011101011100100001110111100001110111111011101111000101101001000000111110111110001100101000100101101001011001011011001101010000000010110110000111110111101 +
b11111011110 #
b11111011110 *
b10101010101010000000000000000000000000000000000000000000000000000000000000000000000000000000000000000000000000000000000000000000000000000000000000000000000000000000000000000000000000000000000000000000000000000000000000000000000000000000000000110010000101110010011000001001001100000110001110110010100011001110110000011111101110010000100001010101000101001010001101110101110010000111011110000111011111101110111100010110100100000011111011111000110010100010010110100101100101101100110101000000001011011000011111011110 -
b1110 '
b10000 %
b10000 /
b1000000 .
b10000000100000001000000010000000100000001000000010000000100000001000000010000000100000001000000010000000100100000000000000010000 &
b10000 !
1"
#155000
0"
#160000
b110000010000 $
b110000010000 0
b1010101010101100000000000000000000000000000000000000000000000000000000000000000000000000000000000000000000000000000000000000000000000000000000000000000000000000000000000000000000000000000000000000000000000000000000000000000000000000000000000110111100110100111111010001111111101000110101100010111011011011100010100011000000100111100111001101010110110111101101100100010100111100110001000100110001000000100010001011010011111000011000001000010110111011011111010011110101110100101110010110000001101001010011000001000 ,
b1010101010110000000000000000000000000000000000000000000000000000000000000000000000000000000000000000000000000000000000000000000000000000000000000000000000000000000000000000000000000000000000000000000000000000000000000000000000000000000000011011110011010011111101000111111110100011010110001011101101101110001010001100000010011110011100110101011011011110110110010001010011110011000100010011000100000010001000101101001111100001100000100001011011101101111101001111010111010010111001011000000110100101001100000100001 +
b110000010000 #
b110000010000 *
b1111 '
b1 %
b1 /
b1000 .
b10000000100000001000000010000000100000001000000010000000100000001000000010000000100000001000000010000000100001000000000000010000 &
b10101010101011000000000000000000000000000000000000000000000000000000000000000000000000000000000000000000000000000000000000000000000000000000000000000000000000000000000000000000000000000000000000000000000000000000000000000000000000000000000001101111001101001111110100011111111010001101011000101110110110111000101000110000001001111001110011010101101101111011011001000101001111001100010001001100010000001000100010110100111110000110000010000101101110110111110100111101011101001011100101100000011010010100110000010000 -
b10001 !
1"
#165000
0"
#170000
b1001000 $
b1001000 0
b11010101010101010000000000000000000000000000000000000000000000000000000000000000000000000000000000000000000000000000000000000000000000000000000000000000000000000000000000000000000000000000000000000000000000000000000000000000000000000000000001100100011100111100000011011000000001101100101010110100010010010010110110110100001111100011100111001010100100100001001011110110111100011101011101111101011100001110111011010011110000100110100011100110100100010010000011110000101000111101001110101000011001111011110100011100 ,
b1010101010101000000000000000000000000000000000000000000000000000000000000000000000000000000000000000000000000000000000000000000000000000000000000000000000000000000000000000000000000000000000000000000000000000000000000000000000000000000000110010001110011110000001101100000000110110010101011010001001001001011011011010000111110001110011100101010010010000100101111011011110001110101110111110101110000111011101101001111000010011010001110011010010001001000001111000010100011110100111010100001100111101111010001110011 +
b11101000111001 #
b11101000111001 *
b10101010101010100000000000000000000000000000000000000000000000000000000000000000000000000000000000000000000000000000000000000000000000000000000000000000000000000000000000000000000000000000000000000000000000000000000000000000000000000000000011001000111001111000000110110000000011011001010101101000100100100101101101101000011111000111001110010101001001000010010111101101111000111010111011111010111000011101110110100111100001001101000111001101001000100100000111100001010001111010011101010000110011110111101000111001 -
b10000 '
b1000 %
b1000 /
b10000000 .
b10000000100000001000000010000000100000001000000010000000100000001000000010000000100000001000000010000000100000001000000000010000 &
b10010 !
1"
#175000
0"
#180000
b1101100111 $
b1101100111 0
b10010101010101011000000000000000000000000000000000000000000000000000000000000000000000000000000000000000000000000000000000000000000000000000000000000000000000000000000000000000000000000000000000000000000000000000000000000000000000000000000011011110110011100010000110010100000011001011101010100110111111111110100100100110011000010110011100111010111111110011111010000100100010110001010001000001010010011000100010011110001001111100110110011100111110111111000110001001101101100001111000101100110111000010000110110011 ,
b1010101010101100000000000000000000000000000000000000000000000000000000000000000000000000000000000000000000000000000000000000000000000000000000000000000000000000000000000000000000000000000000000000000000000000000000000000000000000000000001101111011001110001000011001010000001100101110101010011011111111111010010010011001100001011001110011101011111111001111101000010010001011000101000100000101001001100010001001111000100111110011011001110011111011111100011000100110110110000111100010110011011100001000011011001110 +
b1101100111 #
b1101100111 *
b10001 '
b10000000 %
b10000000 /
b100 .
b10000000100000001000000010000000100000001000000010000000100000001000000010000000100000001000000010000000000010001000000000010000 &
b101010101010110000000000000000000000000000000000000000000000000000000000000000000000000000000000000000000000000000000000000000000000000000000000000000000000000000000000000000000000000000000000000000000000000000000000000000000000000000000110111101100111000100001100101000000110010111010101001101111111111101001001001100110000101100111001110101111111100111110100001001000101100010100010000010100100110001000100111100010011111001101100111001111101111110001100010011011011000011110001011001101110000100001101100111 -
b10011 !
1"
#185000
0"
#190000
b10011001011100 $
b10011001011100 0
b1110101010101010100000000000000000000000000000000000000000000000000000000000000000000000000000000000000000000000000000000000000000000000000000000000000000000000000000000000000000000000000000000000000000000000000000000000000000000000000000110010000101110010111001101110110000110111010001010111100100000000000111111111101110100110101110011100010100000001110000011001111110110101011011011100011011111110101110111110001011111000011100101110011100000100000101101011111001001010011000101101011100100100111001100101110 ,
b11010101010101010000000000000000000000000000000000000000000000000000000000000000000000000000000000000000000000000000000000000000000000000000000000000000000000000000000000000000000000000000000000000000000000000000000000000000000000000000011001000010111001011100110111011000011011101000101011110010000000000011111111110111010011010111001110001010000000111000001100111111011010101101101110001101111111010111011111000101111100001110010111001110000010000010110101111100100101001100010110101110010010011100110010111001 +
b10011001011100 #
b10011001011100 *
b11101010101010101000000000000000000000000000000000000000000000000000000000000000000000000000000000000000000000000000000000000000000000000000000000000000000000000000000000000000000000000000000000000000000000000000000000000000000000000000001100100001011100101110011011101100001101110100010101111001000000000001111111111011101001101011100111000101000000011100000110011111101101010110110111000110111111101011101111100010111110000111001011100111000001000001011010111110010010100110001011010111001001001110011001011100 -
b10010 '
b1 %
b1 /
b1000000 .
b10000000100000001000000010000000100000001000000010000000100000001000000010000000100000001000000010000001000000001000000000010000 &
b10100 !
1"
#195000
0"
#200000
b1110111010011 $
b1110111010011 0
b11000101010101010110000000000000000000000000000000000000000000000000000000000000000000000000000000000000000000000000000000000000000000000000000000000000000000000000000000000000000000000000000000000000000000000000000000000000000000000000001101111001101001110100111001000101001100100011011010100011110000000001100000000001000111100101001110010110110000011001000110111000000100101010010010010110010000000101000100001011010000100110011101001110010001110001101001010000111111011110101101001010011111111100111011101001 ,
b10101010101011000000000000000000000000000000000000000000000000000000000000000000000000000000000000000000000000000000000000000000000000000000000000000000000000000000000000000000000000000000000000000000000000000000000000000000000000000110111100110100111010011100100010100110010001101101010001111000000000110000000000100011110010100111001011011000001100100011011100000010010101001001001011001000000010100010000101101000010011001110100111001000111000110100101000011111101111010110100101001111111110011101110100111 +
b1110111010011 #
b1110111010011 *
b10011 '
b0 %
b0 /
b0 .
b10000000100000001000000010000000100000001000000010000000100000001000000010000000100000001000000010000000000001001000000000010000 &
b10001010101010101100000000000000000000000000000000000000000000000000000000000000000000000000000000000000000000000000000000000000000000000000000000000000000000000000000000000000000000000000000000000000000000000000000000000000000000000000011011110011010011101001110010001010011001000110110101000111100000000011000000000010001111001010011100101101100000110010001101110000001001010100100100101100100000001010001000010110100001001100111010011100100011100011010010100001111110111101011010010100111111111001110111010011 -
b10101 !
1"
#205000
0"
